<?xml version="1.0" encoding="utf-8"?><annotation>  
	  <folder>meshdata(aug)</folder>  
	  <filename>128_3.jpg</filename>  
	  <path>G:\DOCX\GraduationProj\meshdata(aug)\128_3.jpg</path>  
	  <source>    
		    <database>Unknown</database>    
	  </source>  
	  <size>    
		    <width>600</width>    
		    <height>660</height>    
		    <depth>1</depth>    
	  </size>  
	  <segmented>0</segmented>  
	  <object>    
		    <name>mesh</name>    
		    <pose>Unspecified</pose>    
		    <truncated>0</truncated>    
		    <difficult>0</difficult>    
		    <bndbox>      
			      <xmin>158</xmin>      
			      <ymin>193</ymin>      
			      <xmax>307</xmax>      
			      <ymax>343</ymax>      
		    </bndbox>    
	  </object>  
	  <object>    
		    <name>mesh</name>    
		    <pose>Unspecified</pose>    
		    <truncated>0</truncated>    
		    <difficult>0</difficult>    
		    <bndbox>      
			      <xmin>40</xmin>      
			      <ymin>419</ymin>      
			      <xmax>94</xmax>      
			      <ymax>522</ymax>      
		    </bndbox>    
	  </object>  
	  <object>    
		    <name>mesh</name>    
		    <pose>Unspecified</pose>    
		    <truncated>0</truncated>    
		    <difficult>0</difficult>    
		    <bndbox>      
			      <xmin>125</xmin>      
			      <ymin>411</ymin>      
			      <xmax>169</xmax>      
			      <ymax>522</ymax>      
		    </bndbox>    
	  </object>  
	  <object>    
		    <name>mesh</name>    
		    <pose>Unspecified</pose>    
		    <truncated>0</truncated>    
		    <difficult>0</difficult>    
		    <bndbox>      
			      <xmin>299</xmin>      
			      <ymin>468</ymin>      
			      <xmax>421</xmax>      
			      <ymax>548</ymax>      
		    </bndbox>    
	  </object>  
	  <object>    
		    <name>mesh</name>    
		    <pose>Unspecified</pose>    
		    <truncated>0</truncated>    
		    <difficult>0</difficult>    
		    <bndbox>      
			      <xmin>429</xmin>      
			      <ymin>218</ymin>      
			      <xmax>547</xmax>      
			      <ymax>315</ymax>      
		    </bndbox>    
	  </object>  
</annotation>